LICENSE
MANIFEST.in
README.md
requirements.txt
setup.py
tox.ini
peddy/GRCH37.sites
peddy/GRCH37.sites.bin.gz
peddy/GRCH38.sites
peddy/GRCH38.sites.bin.gz
peddy/__init__.py
peddy/__main__.py
peddy/cli.py
peddy/king.py
peddy/pca.py
peddy/peddy.py
peddy/tmpl.html
peddy/tmpl.vs.html
peddy/utils.py
peddy.egg-info/PKG-INFO
peddy.egg-info/SOURCES.txt
peddy.egg-info/dependency_links.txt
peddy.egg-info/entry_points.txt
peddy.egg-info/not-zip-safe
peddy.egg-info/requires.txt
peddy.egg-info/top_level.txt
peddy/tests/__init__.py
peddy/tests/a.ped
peddy/tests/a6.ped
peddy/tests/test-unknown-gma.ped
peddy/tests/test.fam.ped
peddy/tests/test.fam2.ped
peddy/tests/test.mendel.ped
peddy/tests/test.mendel.vcf.gz
peddy/tests/test.mendel.vcf.gz.tbi
peddy/tests/test_peddy.py