Metadata-Version: 2.1
Name: peddy
Version: 0.4.8
Summary: pleasingly pythonic pedigree manipulation
Home-page: UNKNOWN
Author: Brent Pedersen
Author-email: bpederse@gmail.com
License: UNKNOWN
Platform: UNKNOWN
Classifier: Development Status :: 4 - Beta
Classifier: Intended Audience :: Science/Research
Classifier: License :: OSI Approved :: MIT License
Classifier: Topic :: Scientific/Engineering :: Bio-Informatics
